omero/plugins/certificates.py
omero_certificates/__init__.py
omero_certificates/_version.py
omero_certificates/certificates.py
omero_certificates/cli.py
omero_certificates-0.3.2.dist-info/LICENSE.txt
omero_certificates-0.3.2.dist-info/METADATA
omero_certificates-0.3.2.dist-info/WHEEL
omero_certificates-0.3.2.dist-info/top_level.txt
omero_certificates-0.3.2.dist-info/RECORD
